pygmidi/__init__.py
pygmidi/pygmidi.py
pygmidi/repr.py
pygmidi/versionfile.py
pygmidi/midiarray/__init__.py
pygmidi/midiarray/midiarray.py
pygmidi/midiarray/utilities.py
pygmidi/utils/__init__.py
pygmidi/utils/evaltools.py
pygmidi/utils/metrics.py
pygmidi/utils/plot.py
pygmidi/utils/pyormidict.py
pygmidi/utils/sparray.py
pygmidi-4.0.1.dist-info/METADATA
pygmidi-4.0.1.dist-info/WHEEL
pygmidi-4.0.1.dist-info/top_level.txt
pygmidi-4.0.1.dist-info/RECORD
