Metadata-Version: 2.1
Name: pygmidi
Version: 4.0.1
Summary: Python General MIDI representation for symbolic music data analysis
Home-page: http://github.com/LESSSE/pygmidi
Author: Luís Espírito Santo (LESSSE)
Author-email: luis.a.santo@tecnico.ulisboa.pt
License: UNKNOWN
Keywords: general,midi,dataset,music,symbolic,pygmidi
Platform: UNKNOWN
Classifier: Development Status :: 2 - Pre-Alpha
Classifier: License :: Free for non-commercial use
Classifier: Programming Language :: Python :: 2.7
Classifier: Intended Audience :: Education
Classifier: Topic :: Artistic Software
Classifier: Topic :: Multimedia :: Sound/Audio :: MIDI
Requires-Dist: six (<2.0,>=1.0.0)
Requires-Dist: numpy (<2.0,>=1.10.0)
Requires-Dist: scipy (<2.0,>=1.0.0)
Requires-Dist: mido
Requires-Dist: pandas
Requires-Dist: pyfluidsynth
Requires-Dist: scikit-learn
Requires-Dist: six (>=1.0.0)
Requires-Dist: matplotlib
Requires-Dist: pypianoroll
Requires-Dist: python3-midi
Requires-Dist: pretty-midi
Requires-Dist: MIDIUtil
Provides-Extra: gif
Requires-Dist: moviepy (>=0.2.3.2) ; extra == 'gif'
Provides-Extra: plot
Requires-Dist: matplotlib (>=1.5) ; extra == 'plot'
